LICENSE
MANIFEST.in
README.md
setup.cfg
setup.py
versioneer.py
./.gitattributes
./CODE_OF_CONDUCT.md
./CONTRIBUTING.md
./Dockerfile
./LICENSE
./MANIFEST.in
./Makefile
./README.md
./setup.cfg
./setup.py
./versioneer.py
./pdffactory/__init__.py
./pdffactory/_version.py
./pdffactory/pdffactory.py
./pdffactory.egg-info/PKG-INFO
./pdffactory.egg-info/SOURCES.txt
./pdffactory.egg-info/dependency_links.txt
./pdffactory.egg-info/requires.txt
./pdffactory.egg-info/top_level.txt
./tests/__init__.py
./tests/test_pdffactory.py
./tests/data/__init__.py
pdffactory/__init__.py
pdffactory/_version.py
pdffactory/pdffactory.py
pdffactory.egg-info/PKG-INFO
pdffactory.egg-info/SOURCES.txt
pdffactory.egg-info/dependency_links.txt
pdffactory.egg-info/requires.txt
pdffactory.egg-info/top_level.txt
tests/__init__.py
tests/test_pdffactory.py
tests/data/__init__.py