Metadata-Version: 2.1
Name: pdffactory
Version: 0.1.33
Summary: A class to update and/or create a pdf object, and add pages to it
Home-page: https://github.com/Advestis/pdffactory
Author: Advestis
Author-email: pythondev@advestis.com
License: GPLv3
Project-URL: Bug Tracker, https://github.com/Advestis/pdffactory/issues
Project-URL: Documentation, https://advestis.github.io/pdffactory
Project-URL: Source Code, https://github.com/Advestis/pdffactory/
Platform: UNKNOWN
Classifier: Development Status :: 5 - Production/Stable
Classifier: License :: OSI Approved :: GNU General Public License v3 (GPLv3)
Classifier: Operating System :: Unix
Classifier: Programming Language :: Python :: 3.7
Classifier: Programming Language :: Python :: 3.8
Classifier: Programming Language :: Python :: 3.9
Requires-Python: >=3.7
License-File: LICENSE
